mkdocs_manpage-2.0.1.data/data/share/man/man1/mkdocs-manpage.1
mkdocs_manpage-2.0.1.data/data/share/man/man3/mkdocs_manpage.3
mkdocs_manpage-2.0.1.dist-info/METADATA
mkdocs_manpage-2.0.1.dist-info/WHEEL
mkdocs_manpage-2.0.1.dist-info/entry_points.txt
mkdocs_manpage-2.0.1.dist-info/licenses/LICENSE
mkdocs_manpage/__init__.py
mkdocs_manpage/config.py
mkdocs_manpage/debug.py
mkdocs_manpage/logger.py
mkdocs_manpage/plugin.py
mkdocs_manpage/preprocess.py
mkdocs_manpage/py.typed
mkdocs_manpage-2.0.1.dist-info/RECORD
