Metadata-Version: 2.1
Name: mkdocs-manpage
Version: 2.0.1
Summary: MkDocs plugin to generate a manpage from the documentation site.
Author-Email: =?utf-8?q?Timoth=C3=A9e_Mazzucotelli?= <dev@pawamoy.fr>
License: ISC
Classifier: Development Status :: 4 - Beta
Classifier: Intended Audience :: Developers
Classifier: Programming Language :: Python
Classifier: Programming Language :: Python :: 3
Classifier: Programming Language :: Python :: 3 :: Only
Classifier: Programming Language :: Python :: 3.9
Classifier: Programming Language :: Python :: 3.10
Classifier: Programming Language :: Python :: 3.11
Classifier: Programming Language :: Python :: 3.12
Classifier: Programming Language :: Python :: 3.13
Classifier: Programming Language :: Python :: 3.14
Classifier: Topic :: Documentation
Classifier: Topic :: Software Development
Classifier: Topic :: Utilities
Classifier: Typing :: Typed
Project-URL: Homepage, https://pawamoy.github.io/mkdocs-manpage
Project-URL: Documentation, https://pawamoy.github.io/mkdocs-manpage
Project-URL: Changelog, https://pawamoy.github.io/mkdocs-manpage/changelog
Project-URL: Repository, https://github.com/pawamoy/mkdocs-manpage
Project-URL: Issues, https://github.com/pawamoy/mkdocs-manpage/issues
Project-URL: Discussions, https://github.com/pawamoy/mkdocs-manpage/discussions
Project-URL: Gitter, https://gitter.im/mkdocs-manpage/community
Project-URL: Funding, https://github.com/sponsors/pawamoy
Requires-Python: >=3.9
Provides-Extra: preprocess
Requires-Dist: beautifulsoup4>=4.12; extra == "preprocess"
Requires-Dist: lxml>=5.3; extra == "preprocess"
